pyjenkins
