Metadata-Version: 1.1
Name: pyjenkins
Version: 0.1.2
Summary: Python wrapper around the Jenkins JSON API
Home-page: https://github.com/stylecaster/pyjenkins
Author: Chris Lawlor
Author-email: chris.lawlor@stylecaster.com
License: MIT
Keywords: jenkins
Platform: UNKNOWN
Classifier: Development Status :: 2 - Pre-Alpha
Classifier: Intended Audience :: Developers
Classifier: License :: OSI Approved :: BSD License
Classifier: Natural Language :: English
Classifier: Programming Language :: Python :: 2
Classifier: Programming Language :: Python :: 2.6
Classifier: Programming Language :: Python :: 2.7
Classifier: Programming Language :: Python :: 3
Classifier: Programming Language :: Python :: 3.3
